pytest_tzshift/__init__.py
pytest_tzshift/_types.py
pytest_tzshift/plugin.py
pytest_tzshift-0.1.1.dist-info/licenses/LICENSE
pytest_tzshift-0.1.1.dist-info/METADATA
pytest_tzshift-0.1.1.dist-info/WHEEL
pytest_tzshift-0.1.1.dist-info/entry_points.txt
pytest_tzshift-0.1.1.dist-info/top_level.txt
pytest_tzshift-0.1.1.dist-info/RECORD
