Metadata-Version: 2.4
Name: pytest-tzshift
Version: 0.1.1
Summary: A Pytest plugin that transparently re-runs tests under a matrix of timezones and locales.
Author-email: Pedro Sanvido <pedro.sanvido@acad.pucrs.br>
Maintainer-email: Pedro Sanvido <pedro.sanvido@acad.pucrs.br>
License: 
Project-URL: Repository, https://github.com/spedr/pytest-tzshift
Classifier: Framework :: Pytest
Classifier: Development Status :: 4 - Beta
Classifier: Intended Audience :: Developers
Classifier: Topic :: Software Development :: Testing
Classifier: Operating System :: OS Independent
Classifier: Programming Language :: Python
Classifier: Programming Language :: Python :: 3.9
Classifier: Programming Language :: Python :: 3.10
Classifier: Programming Language :: Python :: 3.11
Classifier: Programming Language :: Python :: 3.12
Classifier: Programming Language :: Python :: 3 :: Only
Classifier: Programming Language :: Python :: Implementation :: CPython
Classifier: Programming Language :: Python :: Implementation :: PyPy
Classifier: License :: OSI Approved :: MIT License
Requires-Python: >=3.9
License-File: LICENSE
Requires-Dist: pytest>=7.0
Requires-Dist: backports.zoneinfo>=0.2.1; python_version < "3.9"
Requires-Dist: tzdata>=2024.1
Dynamic: license-file
